combinedpackmsnk/__init__.py
combinedpackmsnk/combinedpackmsnk.py
combinedpackmsnk-0.4.dist-info/METADATA
combinedpackmsnk-0.4.dist-info/WHEEL
combinedpackmsnk-0.4.dist-info/top_level.txt
combinedpackmsnk-0.4.dist-info/RECORD
