Metadata-Version: 2.1
Name: combinedpackmsnk
Version: 0.4
Summary: A comprehensive package for data analysis, visualization, preprocessing, and machine learning to minimize code and maximize insights.
Home-page: https://pypi.org/project/combinedpackmsnk/
Author: mukund14
Author-email: mukundan.sankar14@gmail.com
Classifier: Development Status :: 4 - Beta
Classifier: Intended Audience :: Developers
Classifier: Programming Language :: Python :: 3
Requires-Dist: numpy
Requires-Dist: pandas
Requires-Dist: scikit-learn
Requires-Dist: xgboost
Requires-Dist: statsmodels
Requires-Dist: plotly
Requires-Dist: requests
Requires-Dist: ydata-profiling
